README.rst
setup.py
drone/__init__.py
drone.egg-info/PKG-INFO
drone.egg-info/SOURCES.txt
drone.egg-info/dependency_links.txt
drone.egg-info/top_level.txt
drone/client/__init__.py
drone/plugin/__init__.py
drone/plugin/input.py