Metadata-Version: 1.1
Name: drone
Version: 0.2.0
Summary: Drone CI plugin utilities and HTTP API client
Home-page: https://github.com/gtaylor/drone-python
Author: Greg Taylor
Author-email: gtaylor@gc-taylor.com
License: MIT License
Keywords: drone ci test plugin api
Platform: UNKNOWN
Classifier: Development Status :: 2 - Pre-Alpha
Classifier: Intended Audience :: System Administrators
Classifier: Intended Audience :: Developers
Classifier: License :: OSI Approved :: MIT License
Classifier: Programming Language :: Python :: 2.7
Classifier: Programming Language :: Python :: 3.4
Classifier: Programming Language :: Python :: 3.5
